Workbook
Name receipt_delay: Assumptions!$B$2

Sheet Model
A1: Lumbridge Services: monthly forecast (AUD) | B1: 46296 | C1: 46327 | D1: 46357
A2: Revenue | B2: =Sources!$B$2+Sources!$B$3 -> 60000 | C2: =Sources!$B$2+Sources!$B$3 -> 60000 | D2: =Sources!$B$2+Sources!$B$3 -> 60000
A3: Materials | B3: =-Sources!$B$4 -> 12000 | C3: =-Sources!$B$4 -> 12000 | D3: =-Sources!$B$4 -> 12000
A4: Overhead | B4: =-Sources!$B$5 -> 6000 | C4: =-Sources!$B$5 -> 6000 | D4: =-Sources!$B$5 -> 6000
A5: Gross wages | B5: =-Sources!$B$6 -> 24000 | C5: =-Sources!$B$6 -> 24000 | D5: =-Sources!$B$6 -> 24000
A6: Super | B6: =-Sources!$B$7 -> 2880 | C6: =-Sources!$B$7 -> 2880 | D6: =-Sources!$B$7 -> 2880
A7: Workers compensation | B7: =-Sources!$B$8 -> 480 | C7: =-Sources!$B$8 -> 480 | D7: =-Sources!$B$8 -> 480
A8: Leave provision | B8: =-Sources!$B$9 -> 2254.15 | C8: =-Sources!$B$9 -> 2254.15 | D8: =-Sources!$B$9 -> 2254.15
A9: Depreciation | B9: =-Sources!$B$10 -> 200 | C9: =-Sources!$B$10 -> 200 | D9: =-Sources!$B$10 -> 200
A10: Interest | B10: =-Sources!$B$11 -> 200 | C10: =-Sources!$B$11 -> 200 | D10: =-Sources!$B$11 -> 200
A11: Profit before tax | B11: =B2-SUM(B3:B10) -> 11985.85 | C11: =C2-SUM(C3:C10) -> 11985.85 | D11: =D2-SUM(D3:D10) -> 11985.85
A12: Customer receipts | B12: =SUMIFS('Cash dates'!$D$2:$D$35,'Cash dates'!$C$2:$C$35,">="&DATE(2026,10,1),'Cash dates'!$C$2:$C$35,"<="&DATE(2026,10,31)) -> 66000 | C12: =SUMIFS('Cash dates'!$D$2:$D$35,'Cash dates'!$C$2:$C$35,">="&DATE(2026,11,1),'Cash dates'!$C$2:$C$35,"<="&DATE(2026,11,30)) -> 66000 | D12: =SUMIFS('Cash dates'!$D$2:$D$35,'Cash dates'!$C$2:$C$35,">="&DATE(2026,12,1),'Cash dates'!$C$2:$C$35,"<="&DATE(2026,12,31)) -> 66000
A13: Cash payments | B13: =SUMIFS('Cash dates'!$E$2:$E$35,'Cash dates'!$C$2:$C$35,">="&DATE(2026,10,1),'Cash dates'!$C$2:$C$35,"<="&DATE(2026,10,31)) -> 63960 | C13: =SUMIFS('Cash dates'!$E$2:$E$35,'Cash dates'!$C$2:$C$35,">="&DATE(2026,11,1),'Cash dates'!$C$2:$C$35,"<="&DATE(2026,11,30)) -> 48360 | D13: =SUMIFS('Cash dates'!$E$2:$E$35,'Cash dates'!$C$2:$C$35,">="&DATE(2026,12,1),'Cash dates'!$C$2:$C$35,"<="&DATE(2026,12,31)) -> 48360
A14: Closing cash | B14: =Sources!$B$12+B12-B13 -> 32040 | C14: =B14+C12-C13 -> 49680 | D14: =C14+D12-D13 -> 67320
A15: Receivables | B15: =Sources!$B$13+B2*(1+Sources!$B$20)-B12 -> 66000 | C15: =B15+C2*(1+Sources!$B$20)-C12 -> 66000 | D15: =C15+D2*(1+Sources!$B$20)-D12 -> 66000
A16: Supplier payables | B16: =-Sources!$B$15 -> 13200 | C16: =-Sources!$B$15 -> 13200 | D16: =-Sources!$B$15 -> 13200
A17: GST payable | B17: =-Sources!$B$16+(B2-B3-B4)*Sources!$B$20-SUMIFS('Cash dates'!$E$2:$E$35,'Cash dates'!$F$2:$F$35,"GST settlement",'Cash dates'!$C$2:$C$35,">="&DATE(2026,10,1),'Cash dates'!$C$2:$C$35,"<="&DATE(2026,10,31)) -> 4200 | C17: =B17+(C2-C3-C4)*Sources!$B$20-SUMIFS('Cash dates'!$E$2:$E$35,'Cash dates'!$F$2:$F$35,"GST settlement",'Cash dates'!$C$2:$C$35,">="&DATE(2026,11,1),'Cash dates'!$C$2:$C$35,"<="&DATE(2026,11,30)) -> 8400 | D17: =C17+(D2-D3-D4)*Sources!$B$20-SUMIFS('Cash dates'!$E$2:$E$35,'Cash dates'!$F$2:$F$35,"GST settlement",'Cash dates'!$C$2:$C$35,">="&DATE(2026,12,1),'Cash dates'!$C$2:$C$35,"<="&DATE(2026,12,31)) -> 12600
A18: PAYG withholding payable | B18: =-Sources!$B$17 -> 5000 | C18: =-Sources!$B$17 -> 5000 | D18: =-Sources!$B$17 -> 5000
A19: Loan principal paid | B19: =Sources!$B$21 -> 1000 | C19: =Sources!$B$21 -> 1000 | D19: =Sources!$B$21 -> 1000
A20: Income tax instalment | B20: =Sources!$B$22 -> 3000 | C20: =0 -> 0 | D20: =0 -> 0
A21: Cash from profit bridge | B21: =B11+B9+B8-(B15-Sources!$B$13)+(B17--Sources!$B$16)-B19-B20 -> 2040 | C21: =C11+C9+C8-(C15-B15)+(C17-B17)-C19-C20 -> 17640 | D21: =D11+D9+D8-(D15-C15)+(D17-C17)-D19-D20 -> 17640
A22: Cash reconciliation difference | B22: =B21-B12+B13 -> 0 | C22: =C21-C12+C13 -> 0 | D22: =D21-D12+D13 -> 0
A24: Profit is before income tax. PAYG instalments reduce cash, not pre-tax profit.
A25: GST, supplier and withholding balances remain payable after the forecast.
A26: Select the receipt delay on Assumptions. No actual forecast accuracy has been measured.
A27: Receipt delay (calendar days) | B27: =receipt_delay -> 0

Sheet Cash 13 weeks
A1: Week start | B1: Week end | C1: Receipts AUD | D1: Payments AUD | E1: Net cash AUD | F1: Closing cash AUD | G1: Buffer AUD
A2: 46297 | B2: 46303 | C2: =SUMIFS('Cash dates'!$D$2:$D$35,'Cash dates'!$C$2:$C$35,">="&A2,'Cash dates'!$C$2:$C$35,"<="&B2) -> 0 | D2: =SUMIFS('Cash dates'!$E$2:$E$35,'Cash dates'!$C$2:$C$35,">="&A2,'Cash dates'!$C$2:$C$35,"<="&B2) -> 13200 | E2: =C2-D2 -> -13200 | F2: =Sources!$B$12+E2 -> 16800 | G2: =Assumptions!$B$3 -> 15000
A3: 46304 | B3: 46310 | C3: =SUMIFS('Cash dates'!$D$2:$D$35,'Cash dates'!$C$2:$C$35,">="&A3,'Cash dates'!$C$2:$C$35,"<="&B3) -> 44000 | D3: =SUMIFS('Cash dates'!$E$2:$E$35,'Cash dates'!$C$2:$C$35,">="&A3,'Cash dates'!$C$2:$C$35,"<="&B3) -> 1200 | E3: =C3-D3 -> 42800 | F3: =F2+E3 -> 59600 | G3: =Assumptions!$B$3 -> 15000
A4: 46311 | B4: 46317 | C4: =SUMIFS('Cash dates'!$D$2:$D$35,'Cash dates'!$C$2:$C$35,">="&A4,'Cash dates'!$C$2:$C$35,"<="&B4) -> 22000 | D4: =SUMIFS('Cash dates'!$E$2:$E$35,'Cash dates'!$C$2:$C$35,">="&A4,'Cash dates'!$C$2:$C$35,"<="&B4) -> 12080 | E4: =C4-D4 -> 9920 | F4: =F3+E4 -> 69520 | G4: =Assumptions!$B$3 -> 15000
A5: 46318 | B5: 46324 | C5: =SUMIFS('Cash dates'!$D$2:$D$35,'Cash dates'!$C$2:$C$35,">="&A5,'Cash dates'!$C$2:$C$35,"<="&B5) -> 0 | D5: =SUMIFS('Cash dates'!$E$2:$E$35,'Cash dates'!$C$2:$C$35,">="&A5,'Cash dates'!$C$2:$C$35,"<="&B5) -> 37480 | E5: =C5-D5 -> -37480 | F5: =F4+E5 -> 32040 | G5: =Assumptions!$B$3 -> 15000
A6: 46325 | B6: 46331 | C6: =SUMIFS('Cash dates'!$D$2:$D$35,'Cash dates'!$C$2:$C$35,">="&A6,'Cash dates'!$C$2:$C$35,"<="&B6) -> 0 | D6: =SUMIFS('Cash dates'!$E$2:$E$35,'Cash dates'!$C$2:$C$35,">="&A6,'Cash dates'!$C$2:$C$35,"<="&B6) -> 0 | E6: =C6-D6 -> 0 | F6: =F5+E6 -> 32040 | G6: =Assumptions!$B$3 -> 15000
A7: 46332 | B7: 46338 | C7: =SUMIFS('Cash dates'!$D$2:$D$35,'Cash dates'!$C$2:$C$35,">="&A7,'Cash dates'!$C$2:$C$35,"<="&B7) -> 0 | D7: =SUMIFS('Cash dates'!$E$2:$E$35,'Cash dates'!$C$2:$C$35,">="&A7,'Cash dates'!$C$2:$C$35,"<="&B7) -> 13200 | E7: =C7-D7 -> -13200 | F7: =F6+E7 -> 18840 | G7: =Assumptions!$B$3 -> 15000
A8: 46339 | B8: 46345 | C8: =SUMIFS('Cash dates'!$D$2:$D$35,'Cash dates'!$C$2:$C$35,">="&A8,'Cash dates'!$C$2:$C$35,"<="&B8) -> 44000 | D8: =SUMIFS('Cash dates'!$E$2:$E$35,'Cash dates'!$C$2:$C$35,">="&A8,'Cash dates'!$C$2:$C$35,"<="&B8) -> 1200 | E8: =C8-D8 -> 42800 | F8: =F7+E8 -> 61640 | G8: =Assumptions!$B$3 -> 15000
A9: 46346 | B9: 46352 | C9: =SUMIFS('Cash dates'!$D$2:$D$35,'Cash dates'!$C$2:$C$35,">="&A9,'Cash dates'!$C$2:$C$35,"<="&B9) -> 22000 | D9: =SUMIFS('Cash dates'!$E$2:$E$35,'Cash dates'!$C$2:$C$35,">="&A9,'Cash dates'!$C$2:$C$35,"<="&B9) -> 12080 | E9: =C9-D9 -> 9920 | F9: =F8+E9 -> 71560 | G9: =Assumptions!$B$3 -> 15000
A10: 46353 | B10: 46359 | C10: =SUMIFS('Cash dates'!$D$2:$D$35,'Cash dates'!$C$2:$C$35,">="&A10,'Cash dates'!$C$2:$C$35,"<="&B10) -> 0 | D10: =SUMIFS('Cash dates'!$E$2:$E$35,'Cash dates'!$C$2:$C$35,">="&A10,'Cash dates'!$C$2:$C$35,"<="&B10) -> 21880 | E10: =C10-D10 -> -21880 | F10: =F9+E10 -> 49680 | G10: =Assumptions!$B$3 -> 15000
A11: 46360 | B11: 46366 | C11: =SUMIFS('Cash dates'!$D$2:$D$35,'Cash dates'!$C$2:$C$35,">="&A11,'Cash dates'!$C$2:$C$35,"<="&B11) -> 0 | D11: =SUMIFS('Cash dates'!$E$2:$E$35,'Cash dates'!$C$2:$C$35,">="&A11,'Cash dates'!$C$2:$C$35,"<="&B11) -> 13200 | E11: =C11-D11 -> -13200 | F11: =F10+E11 -> 36480 | G11: =Assumptions!$B$3 -> 15000
A12: 46367 | B12: 46373 | C12: =SUMIFS('Cash dates'!$D$2:$D$35,'Cash dates'!$C$2:$C$35,">="&A12,'Cash dates'!$C$2:$C$35,"<="&B12) -> 44000 | D12: =SUMIFS('Cash dates'!$E$2:$E$35,'Cash dates'!$C$2:$C$35,">="&A12,'Cash dates'!$C$2:$C$35,"<="&B12) -> 1200 | E12: =C12-D12 -> 42800 | F12: =F11+E12 -> 79280 | G12: =Assumptions!$B$3 -> 15000
A13: 46374 | B13: 46380 | C13: =SUMIFS('Cash dates'!$D$2:$D$35,'Cash dates'!$C$2:$C$35,">="&A13,'Cash dates'!$C$2:$C$35,"<="&B13) -> 22000 | D13: =SUMIFS('Cash dates'!$E$2:$E$35,'Cash dates'!$C$2:$C$35,">="&A13,'Cash dates'!$C$2:$C$35,"<="&B13) -> 33960 | E13: =C13-D13 -> -11960 | F13: =F12+E13 -> 67320 | G13: =Assumptions!$B$3 -> 15000
A14: 46381 | B14: 46387 | C14: =SUMIFS('Cash dates'!$D$2:$D$35,'Cash dates'!$C$2:$C$35,">="&A14,'Cash dates'!$C$2:$C$35,"<="&B14) -> 0 | D14: =SUMIFS('Cash dates'!$E$2:$E$35,'Cash dates'!$C$2:$C$35,">="&A14,'Cash dates'!$C$2:$C$35,"<="&B14) -> 0 | E14: =C14-D14 -> 0 | F14: =F13+E14 -> 67320 | G14: =Assumptions!$B$3 -> 15000
A17: Minimum week-end cash | B17: =MIN(F2:F14) -> 16800
A18: Minimum cash on a transaction date | B18: =MIN(Sources!$B$12,'Cash dates'!G2:G35) -> 16800
A19: Week-end balances can hide a shortfall earlier in the week.
A20: Receipt delay (calendar days) | B20: =receipt_delay -> 0

Sheet Assumptions
A1: Lumbridge Services: synthetic Newcastle business | B1: Value
A2: Delay OPEN-V receipt (calendar days) | B2: 0
A3: Cash buffer (AUD) | B3: 15000
A4: Change B2 to 45 to test a late Grand Exchange collection.
A5: Only B2 is an interactive scenario control. Rebuild after changing source data.
A6: All amounts are AUD. No game currency or live Xero connection.
A7: Dates move by calendar days; no holiday or receipt-compliance guarantee.

Sheet Cash dates
A1: Record | B1: Base date | C1: Scenario date | D1: Receipts AUD | E1: Payments AUD | F1: Category | G1: Closing cash on date
A2: PAY-01 | B2: 46302 | C2: =B2+IF(A2="OPEN-V",receipt_delay,0) -> 46302 | D2: 0 | E2: 13200 | F2: Materials | G2: =IF(C2>DATE(2026,12,31),"",Sources!$B$12+SUMIFS('Cash dates'!$D$2:$D$35,'Cash dates'!$C$2:$C$35,"<="&C2)-SUMIFS('Cash dates'!$E$2:$E$35,'Cash dates'!$C$2:$C$35,"<="&C2)) -> 16800
A3: OPEN-V | B3: 46309 | C3: =B3+IF(A3="OPEN-V",receipt_delay,0) -> 46309 | D3: 44000 | E3: 0 | F3: Customer receipt | G3: =IF(C3>DATE(2026,12,31),"",Sources!$B$12+SUMIFS('Cash dates'!$D$2:$D$35,'Cash dates'!$C$2:$C$35,"<="&C3)-SUMIFS('Cash dates'!$E$2:$E$35,'Cash dates'!$C$2:$C$35,"<="&C3)) -> 60800
A4: PAY-02 | B4: 46310 | C4: =B4+IF(A4="OPEN-V",receipt_delay,0) -> 46310 | D4: 0 | E4: 1000 | F4: Loan principal | G4: =IF(C4>DATE(2026,12,31),"",Sources!$B$12+SUMIFS('Cash dates'!$D$2:$D$35,'Cash dates'!$C$2:$C$35,"<="&C4)-SUMIFS('Cash dates'!$E$2:$E$35,'Cash dates'!$C$2:$C$35,"<="&C4)) -> 59600
A5: PAY-03 | B5: 46310 | C5: =B5+IF(A5="OPEN-V",receipt_delay,0) -> 46310 | D5: 0 | E5: 200 | F5: Interest | G5: =IF(C5>DATE(2026,12,31),"",Sources!$B$12+SUMIFS('Cash dates'!$D$2:$D$35,'Cash dates'!$C$2:$C$35,"<="&C5)-SUMIFS('Cash dates'!$E$2:$E$35,'Cash dates'!$C$2:$C$35,"<="&C5)) -> 59600
A6: PAY-05 | B6: 46315 | C6: =B6+IF(A6="OPEN-V",receipt_delay,0) -> 46315 | D6: 0 | E6: 480 | F6: Workers compensation | G6: =IF(C6>DATE(2026,12,31),"",Sources!$B$12+SUMIFS('Cash dates'!$D$2:$D$35,'Cash dates'!$C$2:$C$35,"<="&C6)-SUMIFS('Cash dates'!$E$2:$E$35,'Cash dates'!$C$2:$C$35,"<="&C6)) -> 52520
A7: PAY-04 | B7: 46315 | C7: =B7+IF(A7="OPEN-V",receipt_delay,0) -> 46315 | D7: 0 | E7: 6600 | F7: Overhead | G7: =IF(C7>DATE(2026,12,31),"",Sources!$B$12+SUMIFS('Cash dates'!$D$2:$D$35,'Cash dates'!$C$2:$C$35,"<="&C7)-SUMIFS('Cash dates'!$E$2:$E$35,'Cash dates'!$C$2:$C$35,"<="&C7)) -> 52520
A8: OPEN-F | B8: 46316 | C8: =B8+IF(A8="OPEN-V",receipt_delay,0) -> 46316 | D8: 22000 | E8: 0 | F8: Customer receipt | G8: =IF(C8>DATE(2026,12,31),"",Sources!$B$12+SUMIFS('Cash dates'!$D$2:$D$35,'Cash dates'!$C$2:$C$35,"<="&C8)-SUMIFS('Cash dates'!$E$2:$E$35,'Cash dates'!$C$2:$C$35,"<="&C8)) -> 69520
A9: PAY-06 | B9: 46316 | C9: =B9+IF(A9="OPEN-V",receipt_delay,0) -> 46316 | D9: 0 | E9: 5000 | F9: PAYG withholding | G9: =IF(C9>DATE(2026,12,31),"",Sources!$B$12+SUMIFS('Cash dates'!$D$2:$D$35,'Cash dates'!$C$2:$C$35,"<="&C9)-SUMIFS('Cash dates'!$E$2:$E$35,'Cash dates'!$C$2:$C$35,"<="&C9)) -> 69520
A10: PAY-25 | B10: 46323 | C10: =B10+IF(A10="OPEN-V",receipt_delay,0) -> 46323 | D10: 0 | E10: 12600 | F10: GST settlement | G10: =IF(C10>DATE(2026,12,31),"",Sources!$B$12+SUMIFS('Cash dates'!$D$2:$D$35,'Cash dates'!$C$2:$C$35,"<="&C10)-SUMIFS('Cash dates'!$E$2:$E$35,'Cash dates'!$C$2:$C$35,"<="&C10)) -> 32040
A11: PAY-08 | B11: 46323 | C11: =B11+IF(A11="OPEN-V",receipt_delay,0) -> 46323 | D11: 0 | E11: 2880 | F11: Super | G11: =IF(C11>DATE(2026,12,31),"",Sources!$B$12+SUMIFS('Cash dates'!$D$2:$D$35,'Cash dates'!$C$2:$C$35,"<="&C11)-SUMIFS('Cash dates'!$E$2:$E$35,'Cash dates'!$C$2:$C$35,"<="&C11)) -> 32040
A12: PAY-07 | B12: 46323 | C12: =B12+IF(A12="OPEN-V",receipt_delay,0) -> 46323 | D12: 0 | E12: 19000 | F12: Net wages | G12: =IF(C12>DATE(2026,12,31),"",Sources!$B$12+SUMIFS('Cash dates'!$D$2:$D$35,'Cash dates'!$C$2:$C$35,"<="&C12)-SUMIFS('Cash dates'!$E$2:$E$35,'Cash dates'!$C$2:$C$35,"<="&C12)) -> 32040
A13: PAY-26 | B13: 46323 | C13: =B13+IF(A13="OPEN-V",receipt_delay,0) -> 46323 | D13: 0 | E13: 3000 | F13: Income tax instalment | G13: =IF(C13>DATE(2026,12,31),"",Sources!$B$12+SUMIFS('Cash dates'!$D$2:$D$35,'Cash dates'!$C$2:$C$35,"<="&C13)-SUMIFS('Cash dates'!$E$2:$E$35,'Cash dates'!$C$2:$C$35,"<="&C13)) -> 32040
... A35: DEC-F | B35: 46408 | C35: =B35+IF(A35="OPEN-V",receipt_delay,0) -> 46408 | D35: 22000 | E35: 0 | F35: Customer receipt | G35: =IF(C35>DATE(2026,12,31),"",Sources!$B$12+SUMIFS('Cash dates'!$D$2:$D$35,'Cash dates'!$C$2:$C$35,"<="&C35)-SUMIFS('Cash dates'!$E$2:$E$35,'Cash dates'!$C$2:$C$35,"<="&C35))

Sheet Sources
A1: Synthetic source record | B1: Value | C1: Source / period
A2: Sales - Varrock maintenance | B2: 40000 | C2: data/xero_pl.csv | September 2026
A3: Sales - Falador repairs | B3: 20000 | C3: data/xero_pl.csv | September 2026
A4: Materials | B4: -12000 | C4: data/xero_pl.csv | September 2026
A5: Operating overhead | B5: -6000 | C5: data/xero_pl.csv | September 2026
A6: Wages and Salaries | B6: -24000 | C6: data/xero_pl.csv | September 2026
A7: Superannuation | B7: -2880 | C7: data/xero_pl.csv | September 2026
A8: Workers Compensation | B8: -480 | C8: data/xero_pl.csv | September 2026
A9: Leave provision expense | B9: -2254.15 | C9: data/xero_pl.csv | September 2026
A10: Depreciation | B10: -200 | C10: data/xero_pl.csv | September 2026
A11: Interest expense | B11: -200 | C11: data/xero_pl.csv | September 2026
A12: Business Bank Account | B12: 30000 | C12: data/xero_bs.csv | September 2026
A13: Accounts Receivable | B13: 66000 | C13: data/xero_bs.csv | September 2026
... A22: Income tax instalment in October | B22: 3000 | C22: Synthetic supplied instalment, not a tax calculation
